mcp_server_pe/__init__.py
mcp_server_pe/__main__.py
mcp_server_pe/schema_extract.py
mcp_server_pe/server.py
mcp_server_pe-0.0.3.dist-info/METADATA
mcp_server_pe-0.0.3.dist-info/WHEEL
mcp_server_pe-0.0.3.dist-info/entry_points.txt
mcp_server_pe-0.0.3.dist-info/top_level.txt
mcp_server_pe-0.0.3.dist-info/RECORD
