Metadata-Version: 2.4
Name: mcp-server-pe
Version: 0.0.3
Summary: MCP Server for PE
Requires-Python: >=3.10
Requires-Dist: click>=8.1.8
Requires-Dist: httpx-sse>=0.4.0
Requires-Dist: mcp>=1.6.0
Requires-Dist: pypinyin>=0.54.0
